pycel/__init__.py
pycel/addin.py
pycel/excelcompiler.py
pycel/excelformula.py
pycel/excellib.py
pycel/excelutil.py
pycel/excelwrapper.py
pycel/version.py
pycel/lib/__init__.py
pycel/lib/date_time.py
pycel/lib/engineering.py
pycel/lib/function_helpers.py
pycel/lib/function_info.py
pycel/lib/function_info_data.py
pycel/lib/information.py
pycel/lib/logical.py
pycel/lib/lookup.py
pycel/lib/stats.py
pycel/lib/text.py
pycel-1.0b30.dist-info/LICENSE.txt
pycel-1.0b30.dist-info/METADATA
pycel-1.0b30.dist-info/WHEEL
pycel-1.0b30.dist-info/top_level.txt
pycel-1.0b30.dist-info/RECORD
