Metadata-Version: 2.1
Name: pycel
Version: 1.0b30
Summary: A library for compiling excel spreadsheets to python code & visualizing them as a graph
Home-page: https://github.com/stephenrauch/pycel
Author: Dirk Gorissen, Stephen Rauch
Author-email: dgorissen@gmail.com
Maintainer: Stephen Rauch
Maintainer-email: stephen.rauch+pycel@gmail.com
License: UNKNOWN
Project-URL: Tracker, https://github.com/stephenrauch/pycel/issues
Keywords: excel compiler formula parser
Platform: UNKNOWN
Classifier: Development Status :: 4 - Beta
Classifier: Intended Audience :: Developers
Classifier: License :: OSI Approved :: GNU General Public License v3 (GPLv3)
Classifier: Operating System :: OS Independent
Classifier: Programming Language :: Python
Classifier: Programming Language :: Python :: 3
Classifier: Programming Language :: Python :: 3.6
Classifier: Programming Language :: Python :: 3.7
Classifier: Programming Language :: Python :: 3.8
Classifier: Programming Language :: Python :: 3.9
Classifier: Topic :: Software Development :: Libraries :: Python Modules
Requires-Python: >=3.6
License-File: LICENSE.txt
